projext/__init__.py
projext/__main__.py
projext/cli.py
projext/config.py
projext/exporters/__init__.py
projext/exporters/json_exporter.py
projext/exporters/markdown.py
projext/modes/__init__.py
projext/modes/full.py
projext/scanner.py
projext-0.1.0a0.dist-info/METADATA
projext-0.1.0a0.dist-info/WHEEL
projext-0.1.0a0.dist-info/entry_points.txt
projext-0.1.0a0.dist-info/licenses/LICENSE
projext-0.1.0a0.dist-info/RECORD
